plotly_unbrand
