Metadata-Version: 1.1
Name: plotly-unbrand
Version: 1.0.1
Summary: A small package to remove the branding from plotly plots
Home-page: https://github.com/AKuederle/plotly_unbrand
Author: Arne Küderle
Author-email: a.kuederle@gmail.com
License: LICENSE
Platform: UNKNOWN
Classifier: Development Status :: 5 - Production/Stable
Classifier: Programming Language :: Python :: 3.5
